README.md
setup.cfg
setup.py
gauss_bino_probability/Binomialdistribution.py
gauss_bino_probability/Gaussiandistribution.py
gauss_bino_probability/Generaldistribution.py
gauss_bino_probability/__init__.py
gauss_bino_probability.egg-info/PKG-INFO
gauss_bino_probability.egg-info/SOURCES.txt
gauss_bino_probability.egg-info/dependency_links.txt
gauss_bino_probability.egg-info/not-zip-safe
gauss_bino_probability.egg-info/top_level.txt