Metadata-Version: 1.0
Name: gauss-bino-probability
Version: 0.1
Summary: Gaussian distributions
Home-page: UNKNOWN
Author: Nischal Mishra
Author-email: UNKNOWN
License: UNKNOWN
Platform: UNKNOWN
